pulumiverse_scaleway/__init__.py
pulumiverse_scaleway/_inputs.py
pulumiverse_scaleway/_utilities.py
pulumiverse_scaleway/account_project.py
pulumiverse_scaleway/account_ssh_key.py
pulumiverse_scaleway/apple_silicon_server.py
pulumiverse_scaleway/baremetal_server.py
pulumiverse_scaleway/block_snapshot.py
pulumiverse_scaleway/block_volume.py
pulumiverse_scaleway/cockpit.py
pulumiverse_scaleway/cockpit_alert_manager.py
pulumiverse_scaleway/cockpit_grafana_user.py
pulumiverse_scaleway/cockpit_source.py
pulumiverse_scaleway/cockpit_token.py
pulumiverse_scaleway/container.py
pulumiverse_scaleway/container_cron.py
pulumiverse_scaleway/container_domain.py
pulumiverse_scaleway/container_namespace.py
pulumiverse_scaleway/container_token.py
pulumiverse_scaleway/container_trigger.py
pulumiverse_scaleway/database.py
pulumiverse_scaleway/database_acl.py
pulumiverse_scaleway/database_backup.py
pulumiverse_scaleway/database_instance.py
pulumiverse_scaleway/database_privilege.py
pulumiverse_scaleway/database_read_replica.py
pulumiverse_scaleway/database_user.py
pulumiverse_scaleway/domain_record.py
pulumiverse_scaleway/domain_zone.py
pulumiverse_scaleway/edge_services_backend_stage.py
pulumiverse_scaleway/edge_services_cache_stage.py
pulumiverse_scaleway/edge_services_dns_stage.py
pulumiverse_scaleway/edge_services_head_stage.py
pulumiverse_scaleway/edge_services_pipeline.py
pulumiverse_scaleway/edge_services_plan.py
pulumiverse_scaleway/edge_services_route_stage.py
pulumiverse_scaleway/edge_services_tls_stage.py
pulumiverse_scaleway/edge_services_waf_stage.py
pulumiverse_scaleway/file_filesystem.py
pulumiverse_scaleway/flexible_ip.py
pulumiverse_scaleway/flexible_ip_mac_address.py
pulumiverse_scaleway/function.py
pulumiverse_scaleway/function_cron.py
pulumiverse_scaleway/function_domain.py
pulumiverse_scaleway/function_namespace.py
pulumiverse_scaleway/function_token.py
pulumiverse_scaleway/function_trigger.py
pulumiverse_scaleway/get_account_project.py
pulumiverse_scaleway-1.42.0.dist-info/METADATA
pulumiverse_scaleway-1.42.0.dist-info/WHEEL
pulumiverse_scaleway-1.42.0.dist-info/top_level.txt
pulumiverse_scaleway-1.42.0.dist-info/RECORD
