Metadata-Version: 2.4
Name: pulumiverse_scaleway
Version: 1.42.0
Summary: A Pulumi package for creating and managing Scaleway cloud resources.
License: Apache-2.0
Project-URL: Homepage, https://www.scaleway.com
Project-URL: Repository, https://github.com/pulumiverse/pulumi-scaleway
Keywords: pulumi,scaleway,pulumiverse
Requires-Python: >=3.9
Requires-Dist: parver>=0.2.1
Requires-Dist: pulumi<4.0.0,>=3.0.0
Requires-Dist: semver>=2.8.1
Requires-Dist: typing-extensions<5,>=4.11; python_version < "3.11"
